clipcrop/__init__.py
clipcrop/clipcrop.py
clipcrop/clipseg.py
clipcrop/components.py
clipcrop-2.5.0.dist-info/LICENSE
clipcrop-2.5.0.dist-info/METADATA
clipcrop-2.5.0.dist-info/WHEEL
clipcrop-2.5.0.dist-info/top_level.txt
clipcrop-2.5.0.dist-info/RECORD
