Metadata-Version: 2.1
Name: clipcrop
Version: 2.5.0
Summary: Extract sections from your image by using OpenAI CLIP and Facebooks Detr implemented on HuggingFace Transformers
Home-page: https://github.com/Vishnunkumar/clipcrop/
Author: Vishnu Nandakumar
Author-email: nkumarvishnu25@gmail.com
License: MIT license
Keywords: clipcrop
Classifier: Development Status :: 3 - Alpha
Classifier: Intended Audience :: Developers
Classifier: Topic :: Software Development :: Build Tools
Classifier: License :: OSI Approved :: MIT License
Classifier: Programming Language :: Python :: 3
Classifier: Programming Language :: Python :: 3.4
Classifier: Programming Language :: Python :: 3.5
Classifier: Programming Language :: Python :: 3.6
License-File: LICENSE
Requires-Dist: transformers
Requires-Dist: torch
Requires-Dist: pillow
Requires-Dist: timm
Requires-Dist: numpy
Requires-Dist: opencv-python
Requires-Dist: pytesseract
